pysicgl/_core.pypy37-pp73-x86_64-linux-gnu.so
pysicgl/__init__.py
pysicgl-0.1.0.dist-info/LICENSE
pysicgl-0.1.0.dist-info/METADATA
pysicgl-0.1.0.dist-info/RECORD
pysicgl-0.1.0.dist-info/top_level.txt
pysicgl-0.1.0.dist-info/WHEEL
