Metadata-Version: 2.1
Name: pysicgl
Version: 0.1.0
Summary: sicgl for Python
Author-email: oclyke <oclyke@oclyke.dev>
Project-URL: Source, https://github.com/oclyke/pysicgl
Keywords: sicgl,2d,2D,small,iterator,graphics,library,c,extension
Classifier: Topic :: Multimedia :: Graphics
Classifier: Programming Language :: Python :: 3
Classifier: License :: OSI Approved :: MIT License
Classifier: Development Status :: 3 - Alpha
Requires-Python: >=3.7
License-File: LICENSE
